{
  "/_not-found/page": "app/_not-found/page.js",
  "/page": "app/page.js",
  "/api/admin/[...path]/route": "app/api/admin/[...path]/route.js",
  "/dashboard/page": "app/dashboard/page.js",
  "/dashboard/appeals/page": "app/dashboard/appeals/page.js",
  "/dashboard/settings/page": "app/dashboard/settings/page.js",
  "/dashboard/staff/page": "app/dashboard/staff/page.js",
  "/dashboard/logs/page": "app/dashboard/logs/page.js",
  "/dashboard/categories/page": "app/dashboard/categories/page.js",
  "/dashboard/panels/page": "app/dashboard/panels/page.js"
}